{
  "main_characters": [
    {
      "नाम": "राधिका शर्मा",
      "उम्र": 32,
      "लिंग": "महिला",
      "पृष्ठभूमि": "राधिका का जन्म उत्तर प्रदेश के एक छोटे से गाँव में हुआ था। वह एक मध्यम वर्गीय परिवार से आती हैं, जो पारंपरिक मूल्यों में विश्वास रखता है। उनके परिवार में शिक्षा को विशेष महत्व दिया जाता है।",
      "शारीरिक वर्णन": "राधिका लंबी और मध्यम कद-काठी वाली महिला हैं। उनके घने काले बाल और गहरी आँखें हैं। उनका व्यक्तित्व आकर्षक है।",
      "व्यक्तित्व गुण": "राधिका गंभीर, मेहनती, और दृढ़ निश्चयी हैं। वह अपनी जिम्मेदारियों को बखूबी निभाती हैं और परिवार के प्रति समर्पित हैं।",
      "प्राथमिक प्रेरणाएँ और इच्छाएँ": "राधिका चाहती हैं कि उनका परिवार खुश और सुरक्षित रहे। वह समाज में महिलाओं के अधिकारों के लिए आवाज उठाना चाहती हैं।",
      "व्यक्तिगत और कथा लक्ष्य": "राधिका की इच्छा है कि वह अपने गाँव में लड़कियों की शिक्षा के लिए एक स्कूल खोल सकें।",
      "आंतरिक और बाहरी संघर्ष": "राधिका का आंतरिक संघर्ष उनकी पारिवारिक जिम्मेदारियों और व्यक्तिगत आकांक्षाओं के बीच है। बाहरी संघर्ष समाज के पारंपरिक सोच के खिलाफ है।",
      "चरित्र आर्क": "कहानी के दौरान, राधिका अपने खुद के संकोचों को पार करती हैं और अपने लक्ष्यों को प्राप्त करने की दिशा में साहसिक कदम उठाती हैं।",
      "संस्कृतिक विशेषताएँ": "राधिका परिवारिक मूल्यों को महत्व देती हैं और त्योहारों में सक्रिय रूप से भाग लेती हैं।",
      "बोलने का तरीका": "राधिका का भाषण सरल और प्रभावी होता है। वह हिंदी में जटिल मुद्दों को सहजता से समझाने की कला रखती हैं।",
      "अन्य पात्रों के साथ संबंध": "राधिका अपने पति और बच्चों के साथ मधुर संबंध रखती हैं लेकिन अपने ससुराल वालों के साथ मतभेद महसूस करती हैं।",
      "शैली के आदर्श पात्र": "राधिका एक नारीवादी नायिका का प्रतिनिधित्व करती हैं जो परिवार और समाज को बदलने का प्रयास करती है।",
      "शैली के तत्वों का अवतार": "राधिका का चरित्र नाटक और सामाजिक टिप्पणी के तत्वों को जोड़ता है, जो परिवार और समाज के बीच की जटिलताओं को दर्शाता है।",
      "विशिष्ट आदतें": "राधिका प्रतिदिन सुबह योग करती हैं और हर शाम अपने बच्चों के साथ समय बिताती हैं।",
      "आवाज की विशेषताएं": "राधिका की आवाज दृढ़ और आत्मविश्वास से भरी है, जो उनके आश्वासन और दृढ़ संकल्प को दर्शाती है।",
      "genre_archetypes": "Cultural Archetype",
      "genre_traits": "Emotionally expressive",
      "narrative_role": "Story Catalyst",
      "emotional_landscape": "Deeply layered emotional landscape with intense internal conflicts"
    },
    {
      "नाम": "अनन्या सिंह",
      "उम्र": 28,
      "लिंग": "महिला",
      "पृष्ठभूमि": "अनन्या का जन्म लखनऊ में हुआ था और उन्होंने अपनी शिक्षा दिल्ली विश्वविद्यालय से प्राप्त की है। वह एक प्रगतिवादी परिवार से आती हैं जहाँ विचारों की स्वतंत्रता को प्रोत्साहित किया जाता है।",
      "शारीरिक वर्णन": "अनन्या की छरहरी कद-काठी है, मध्यम ऊँचाई और हल्की भूरी आँखें हैं। उनका व्यक्तित्व मिलनसार है।",
      "व्यक्तित्व गुण": "अनन्या जीवंत, आत्मनिर्भर और विचारशील हैं। वह अपने करियर में महत्वाकांक्षी हैं और समाज में बदलाव लाने के लिए प्रतिबद्ध हैं।",
      "प्राथमिक प्रेरणाएँ और इच्छाएँ": "अनन्या चाहती हैं कि वह अपनी पेशेवर पहचान बनाएं और समाज में जेंडर इक्वलिटी के लिए काम करें।",
      "व्यक्तिगत और कथा लक्ष्य": "अनन्या का लक्ष्य है कि वह एक सफल वकील बनें और महिलाओं के अधिकारों के लिए कानूनी सहायता प्रदान करें।",
      "आंतरिक और बाहरी संघर्ष": "अनन्या अपने व्यक्तिगत जीवन और पेशेवर प्रतिबद्धताओं के बीच संतुलन बनाने का संघर्ष करती हैं।",
      "चरित्र आर्क": "कहानी के दौरान, अनन्या अपनी असुरक्षाओं पर विजय पाती हैं और एक मजबूत सामाजिक अधिवक्ता के रूप में उभरती हैं।",
      "संस्कृतिक विशेषताएँ": "अनन्या भारतीय परंपराओं का सम्मान करती हैं लेकिन आधुनिक दृष्टिकोण भी अपनाती हैं।",
      "बोलने का तरीका": "अनन्या की भाषा स्पष्ट और तर्कसंगत होती है। वह अक्सर अंग्रेजी और हिंदी के मिश्रण का उपयोग करती हैं।",
      "अन्य पात्रों के साथ संबंध": "अनन्या की राधिका के साथ गहरी मित्रता है और वह अक्सर राधिका के परिवारिक मुद्दों में मदद करती हैं।",
      "शैली के आदर्श पात्र": "अनन्या एक प्रगतिशील चरित्र का प्रतिनिधित्व करती हैं जो सामाजिक परिवर्तन के लिए कार्यरत है।",
      "शैली के तत्वों का अवतार": "अनन्या का चरित्र नाटक और सामाजिक टिप्पणी के तत्वों को मिश्रित करता है, जो सामाजिक असमानताओं के प्रति जागरूकता बढ़ाता है।",
      "विशिष्ट आदतें": "अनन्या हर सुबह समाचार पत्र पढ़ती हैं और अपने विचार ब्लॉग में लिखती हैं।",
      "आवाज की विशेषताएं": "अनन्या की आवाज में स्पष्टता और दृढ़ता होती है, जो उनके न्याय और समानता के प्रति समर्पण को दर्शाती है।",
      "genre_archetypes": "Cultural Archetype",
      "genre_traits": "Emotionally expressive",
      "narrative_role": "Story Catalyst",
      "emotional_landscape": "Deeply layered emotional landscape with intense internal conflicts"
    },
    {
      "नाम": "दादी अम्मा",
      "उम्र": 75,
      "लिंग": "महिला",
      "पृष्ठभूमि": "दादी अम्मा का जन्म एक स्वतंत्रता सेनानी परिवार में हुआ था। वह एक गाँव की प्रतिष्ठित परिवार की सदस्य हैं और उनकी शादी भी एक सामाजिक कार्यकर्ता से हुई थी।",
      "शारीरिक वर्णन": "दादी अम्मा का चेहरा झुर्रियों से भरा है और बाल सफेद हैं। उनकी आँखों में अनुभव की चमक है और उनकी आवाज मधुर है।",
      "व्यक्तित्व गुण": "दादी अम्मा धैर्यवान, बुद्धिमान और करुणामयी हैं। वह पारिवारिक परंपराओं की संरक्षक हैं।",
      "प्राथमिक प्रेरणाएँ और इच्छाएँ": "दादी अम्मा चाहती हैं कि उनका परिवार एकजुट रहे और वह अपने अनुभवों से परिवार को मार्गदर्शन दें।",
      "व्यक्तिगत और कथा लक्ष्य": "दादी अम्मा का उद्देश्य है कि वह परिवार की जड़ों को मजबूती से पकड़कर रखें और नई पीढ़ी को अपने अनुभव बांटें।",
      "आंतरिक और बाहरी संघर्ष": "दादी अम्मा का आंतरिक संघर्ष उनकी पुरानी परंपराओं और नई पीढ़ी की आधुनिक सोच के बीच है।",
      "चरित्र आर्क": "कहानी के दौरान, दादी अम्मा नई पीढ़ी के दृष्टिकोण को समझने और उसे अपनाने की कोशिश करती हैं।",
      "संस्कृतिक विशेषताएँ": "दादी अम्मा भारतीय त्योहारों और रीति-रिवाजों में विश्वास रखती हैं और उन्हें धूमधाम से मनाती हैं।",
      "बोलने का तरीका": "दादी अम्मा की भाषा सरल और अनुभवजन्य होती है। वह अक्सर कहानियों और लोककथाओं का उपयोग करती हैं।",
      "अन्य पात्रों के साथ संबंध": "दादी अम्मा का राधिका और अनन्या के साथ स्नेहपूर्ण संबंध है, और वह उन्हें जीवन के सबक सिखाती हैं।",
      "शैली के आदर्श पात्र": "दादी अम्मा एक पारिवारिक गाइड हैं जो पारिवारिक गाथा और परंपराओं को जीवित रखती हैं।",
      "शैली के तत्वों का अवतार": "दादी अम्मा का चरित्र पारिवारिक गाथा और सामाजिक टिप्पणी के तत्वों को जोड़ता है, जो पारिवारिक मूल्यों को संजोता है।",
      "विशिष्ट आदतें": "दादी अम्मा प्रातःकाल प्रार्थना करती हैं और हर रात अपने पोते-पोतियों को कहानियाँ सुनाती हैं।",
      "आवाज की विशेषताएं": "दादी अम्मा की आवाज में सौम्यता और अनुभवजन्य गहराई होती है, जो उनके जीवन के अनुभवों को प्रदर्शित करती है।",
      "genre_archetypes": "Cultural Archetype",
      "genre_traits": "Emotionally expressive",
      "narrative_role": "Story Catalyst",
      "emotional_landscape": "Deeply layered emotional landscape with intense internal conflicts"
    }
  ],
  "supporting_characters": [
    {
      "नाम": "विजय प्रताप सिंह",
      "कहानी में भूमिका": "परिवार के मुखिया और राधिका के चाचा",
      "मुख्य पात्रों के साथ संबंध": "राधिका के पिता के छोटे भाई हैं और अपनी भतीजी के प्रति गहरी चिंता रखते हैं।",
      "संक्षिप्त पृष्ठभूमि और व्यक्तित्व": "विजय एक अनुशासित और सख्त व्यक्ति हैं, जिन्होंने अपने जीवन में कई संघर्ष देखे हैं। वह पारिवारिक शांति के समर्थक हैं और हमेशा परिवार की भलाई के लिए तत्पर रहते हैं।",
      "उत्तर भारत के सांस्कृतिक पृष्ठभूमि": "विजय प्रताप सिंह का जन्म राजस्थान के एक छोटे से गाँव में हुआ था, जहाँ पारिवारिक मूल्य और परंपराएँ बहुत महत्वपूर्ण मानी जाती हैं।",
      "कथानक को कैसे प्रभावित करते हैं": "विजय परिवार को टूटने से बचाने की कोशिश करते हैं और राधिका के जीवन में महत्वपूर्ण निर्णयों में शामिल होते हैं।",
      "विधा-विशिष्ट कार्य": "पारिवारिक गाइड और संरक्षक के रूप में भूमिका निभाते हैं।",
      "कहानी के विधा तत्वों में योगदान": "परिवार सागा में एक स्थिर स्तंभ के रूप में खड़े होते हैं और सामाजिक टिप्पणी के माध्यम से पारिवारिक मूल्य को उजागर करते हैं।",
      "विशिष्ट भाषण पैटर्न या अभिव्यक्तियाँ": "विजय अक्सर कहेंगे, 'परिवार सबसे पहले आता है,' जिससे उनकी प्राथमिकताओं का पता चलता है।",
      "अध्याय(अध्यायों) में प्रमुख रूप से प्रकट होते हैं": "अध्याय 2 और 4 में विजय की प्रमुख भूमिका है।",
      "प्रमुख दृश्य या इंटरैक्शन": "विजय की राधिका के साथ बातचीत जहाँ वह उसे भविष्य के लिए सलाह देते हैं और परिवार की महत्वता समझाते हैं।",
      "genre_role": "Drama Supporting Character",
      "genre_purpose": "Enhances cultural authenticity",
      "narrative_role": "Story Catalyst",
      "emotional_landscape": "Deeply layered emotional landscape with intense internal conflicts"
    },
    {
      "नाम": "सुमन शर्मा",
      "कहानी में भूमिका": "राधिका की सहेली और विश्वासपात्र",
      "मुख्य पात्रों के साथ संबंध": "राधिका की स्कूल से सहेली और उसके सभी राज़ की रखवाली।",
      "संक्षिप्त पृष्ठभूमि और व्यक्तित्व": "सुमन एक खुशमिजाज और संवेदनशील लड़की है, जिसे जीवन के छोटे-छोटे पलों में खुशी मिलती है।",
      "उत्तर भारत के सांस्कृतिक पृष्ठभूमि": "दिल्ली में जन्मी सुमन उत्तर भारतीय संस्कृति से ओत-प्रोत हैं और हिंदी साहित्य की शौकीन हैं।",
      "कथानक को कैसे प्रभावित करते हैं": "राधिका के जीवन में कठिनाई के समय भावनात्मक समर्थन प्रदान करती हैं।",
      "विधा-विशिष्ट कार्य": "नायक की सहेली और भावनात्मक समर्थन के रूप में कार्य करती हैं।",
      "कहानी के विधा तत्वों में योगदान": "ड्रामा और फैमिली सागा के तत्वों को प्रबल करती हैं, खासकर जब राधिका की भावनात्मक स्थिति को उजागर करती हैं।",
      "विशिष्ट भाषण पैटर्न या अभिव्यक्तियाँ": "सुमन अक्सर कहती हैं, 'खुश रहो, क्योंकि यह भी बीत जाएगा,' जो उनकी सकारात्मकता को दर्शाता है।",
      "अध्याय(अध्यायों) में प्रमुख रूप से प्रकट होते हैं": "अध्याय 3 और 5 में सुमन की भूमिका महत्वपूर्ण है।",
      "प्रमुख दृश्य या इंटरैक्शन": "राधिका के साथ भावनात्मक संवाद जहाँ वह सुमन से अपनी चिंताओं को साझा करती है।",
      "genre_role": "Drama Supporting Character",
      "genre_purpose": "Enhances cultural authenticity",
      "narrative_role": "Story Catalyst",
      "emotional_landscape": "Deeply layered emotional landscape with intense internal conflicts"
    },
    {
      "नाम": "रामजी लाल",
      "कहानी में भूमिका": "गाँव के मुखिया और सामाजिक टिप्पणीकार",
      "मुख्य पात्रों के साथ संबंध": "गाँव में सभी का मार्गदर्शन करते हैं और राधिका के परिवार के पुराने मित्र हैं।",
      "संक्षिप्त पृष्ठभूमि और व्यक्तित्व": "रामजी लाल एक अनुभवी और समझदार व्यक्ति हैं, जो समाज की भलाई के लिए काम करते हैं।",
      "उत्तर भारत के सांस्कृतिक पृष्ठभूमि": "वह उत्तर प्रदेश के एक प्रतिष्ठित गाँव से आते हैं, जहाँ पारंपरिक और आधुनिक विचारधारा का समन्वय है।",
      "कथानक को कैसे प्रभावित करते हैं": "समाज में हो रहे परिवर्तनों पर ध्यान केंद्रित करते हैं और राधिका के परिवार को नई दिशा दिखाते हैं।",
      "विधा-विशिष्ट कार्य": "समाज के संरक्षक और समाजशास्त्रीय दृष्टिकोण के प्रतिनिधि।",
      "कहानी के विधा तत्वों में योगदान": "सामाजिक टिप्पणी और पारिवारिक गाथा में एक महत्वपूर्ण भूमिका निभाते हैं।",
      "विशिष्ट भाषण पैटर्न या अभिव्यक्तियाँ": "रामजी अक्सर कहेंगे, 'समाज की भलाई में ही सबकी भलाई है,' जो उनकी सोच को दर्शाता है।",
      "अध्याय(अध्यायों) में प्रमुख रूप से प्रकट होते हैं": "अध्याय 1 और 6 में रामजी लाल की उपस्थिति महत्वपूर्ण है।",
      "प्रमुख दृश्य या इंटरैक्शन": "गाँव की सभा में भाषण जहाँ वह समाज के मुद्दों पर चर्चा करते हैं।",
      "genre_role": "Drama Supporting Character",
      "genre_purpose": "Enhances cultural authenticity",
      "narrative_role": "Story Catalyst",
      "emotional_landscape": "Deeply layered emotional landscape with intense internal conflicts"
    },
    {
      "नाम": "नैना देवी",
      "कहानी में भूमिका": "राधिका की गुरु और मार्गदर्शिका",
      "मुख्य पात्रों के साथ संबंध": "राधिका की शिक्षिका और जीवन की कठिनाइयों में उसकी सहयोगी।",
      "संक्षिप्त पृष्ठभूमि और व्यक्तित्व": "नैना देवी एक दयालु और बुद्धिमान महिला हैं, जो अपने छात्रों के उज्ज्वल भविष्य के लिए समर्पित हैं।",
      "उत्तर भारत के सांस्कृतिक पृष्ठभूमि": "वह हिमाचल प्रदेश की पहाड़ी संस्कृति से प्रभावित हैं और अपने शिक्षा के तरीकों में सांस्कृतिक तत्वों को शामिल करती हैं।",
      "कथानक को कैसे प्रभावित करते हैं": "राधिका को जीवन में सही दिशा दिखाती हैं और उसे आत्मविश्वास देती हैं।",
      "विधा-विशिष्ट कार्य": "गुरु के रूप में मार्गदर्शन करती हैं।",
      "कहानी के विधा तत्वों में योगदान": "ड्रामा और फैमिली सागा के तत्वों को गहराई प्रदान करती हैं।",
      "विशिष्ट भाषण पैटर्न या अभिव्यक्तियाँ": "वह अक्सर कहती हैं, 'ज्ञान ही सबसे बड़ा धन है,' जो उनके शिक्षण की मूल भावना को दर्शाता है।",
      "अध्याय(अध्यायों) में प्रमुख रूप से प्रकट होते हैं": "अध्याय 4 और 7 में नैना देवी की महत्वपूर्ण भूमिका है।",
      "प्रमुख दृश्य या इंटरैक्शन": "राधिका के साथ कक्षा के बाद की बातचीत, जहाँ वह उसे जीवन के सबक देती हैं।",
      "genre_role": "Drama Supporting Character",
      "genre_purpose": "Enhances cultural authenticity",
      "narrative_role": "Story Catalyst",
      "emotional_landscape": "Deeply layered emotional landscape with intense internal conflicts"
    },
    {
      "नाम": "अशोक कुमार",
      "कहानी में भूमिका": "गाँव के प्रतिद्वंदी और राधिका के परिवार के आलोचक",
      "मुख्य पात्रों के साथ संबंध": "विजय प्रताप सिंह के पुराने प्रतिद्वंद्वी और राधिका के परिवार के खिलाफ षड्यंत्रकारी।",
      "संक्षिप्त पृष्ठभूमि और व्यक्तित्व": "अशोक एक चालाक और महत्वाकांक्षी व्यक्ति हैं, जो सत्ता और शक्ति के भूखे हैं।",
      "उत्तर भारत के सांस्कृतिक पृष्ठभूमि": "वह हरियाणा के एक समृद्ध परिवार से आते हैं और उनके पास परंपराओं और आधुनिकता का मिश्रण है।",
      "कथानक को कैसे प्रभावित करते हैं": "कहानी में तनाव और संघर्ष का कारण बनते हैं और परिवार को विभाजित करने की कोशिश करते हैं।",
      "विधा-विशिष्ट कार्य": "प्रतिद्वंदी के रूप में संघर्ष का कारण बनते हैं।",
      "कहानी के विधा तत्वों में योगदान": "सामाजिक टिप्पणी और ड्रामा में तनाव का निर्माण करते हैं।",
      "विशिष्ट भाषण पैटर्न या अभिव्यक्तियाँ": "अशोक कहते हैं, 'सत्ता ही सब कुछ है,' जो उनकी महत्वाकांक्षा को दर्शाता है।",
      "अध्याय(अध्यायों) में प्रमुख रूप से प्रकट होते हैं": "अध्याय 5 और 8 में अशोक कुमार का महत्वपूर्ण योगदान है।",
      "प्रमुख दृश्य या इंटरैक्शन": "गाँव की पंचायत में अशोक की विजय के साथ बहस, जहाँ वे अपने विचार प्रस्तुत करते हैं।",
      "genre_role": "Drama Supporting Character",
      "genre_purpose": "Enhances cultural authenticity",
      "narrative_role": "Story Catalyst",
      "emotional_landscape": "Deeply layered emotional landscape with intense internal conflicts"
    }
  ]
}